<?xml version="1.0" encoding="UTF-8" standalone="no"?>
<!DOCTYPE properties SYSTEM "http://java.sun.com/dtd/properties.dtd">
<properties>
<comment>Saved</comment>
<entry key="20160602">20160602 김길순 편집부 33000000 0.2 39600000</entry>
<entry key="20150212">20150212 박길동 기획부 48000000 0.2 57600000</entry>
<entry key="20190417">20190417 홍길동 재정부 38000000 0.2 45600000</entry>
<entry key="20170212">20170212 오길현 기획부 32000000 0.2 38400000</entry>
<entry key="20120428">20120428 홍길주 출판부 28000000 0.2 33600000</entry>
</properties>
